markflow/__init__.py
markflow/__main__.py
markflow/_argparse.py
markflow/_utils/__init__.py
markflow/_utils/_utils.py
markflow/_utils/textwrap.py
markflow/detectors/__init__.py
markflow/detectors/_lines.py
markflow/detectors/atx_heading.py
markflow/detectors/blank_line.py
markflow/detectors/block_quote.py
markflow/detectors/bullet_list.py
markflow/detectors/fenced_code_block.py
markflow/detectors/indented_code_block.py
markflow/detectors/link_reference_definition.py
markflow/detectors/ordered_list.py
markflow/detectors/paragraph.py
markflow/detectors/setext_heading.py
markflow/detectors/table.py
markflow/detectors/thematic_break.py
markflow/exceptions.py
markflow/formatters/__init__.py
markflow/formatters/atx_heading.py
markflow/formatters/base.py
markflow/formatters/blank_line.py
markflow/formatters/block_quote.py
markflow/formatters/fenced_code_block.py
markflow/formatters/indented_code_block.py
markflow/formatters/link_reference_definition.py
markflow/formatters/lists.py
markflow/formatters/paragraph.py
markflow/formatters/setext_heading.py
markflow/formatters/table.py
markflow/formatters/thematic_break.py
markflow/parser.py
markflow/reformat_markdown.py
markflow/typing.py
markflow-0.2.1.dist-info/entry_points.txt
markflow-0.2.1.dist-info/LICENSE.txt
markflow-0.2.1.dist-info/WHEEL
markflow-0.2.1.dist-info/METADATA
markflow-0.2.1.dist-info/RECORD
