Metadata-Version: 2.1
Name: markflow
Version: 0.2.1
Summary: Make your Markdown Sparkle!
Author: Joshua Holland
Author-email: jholland@duosecurity.com
Requires-Python: >=3.6,<4.0
Classifier: Programming Language :: Python :: 3
Classifier: Programming Language :: Python :: 3.10
Classifier: Programming Language :: Python :: 3.6
Classifier: Programming Language :: Python :: 3.7
Classifier: Programming Language :: Python :: 3.8
Classifier: Programming Language :: Python :: 3.9
Requires-Dist: pygments
Requires-Dist: rich
